[
  //All units
  {
		"name": "Heal Instantly",
		"uniques": ["[This Unit] heals [50] HP"],
		"unitTypes": ["Sword","Gunpowder","Mounted","Scout","Siege","Archery","Ranged Gunpowder","Armored","Melee Water","Ranged Water","Submarine"],
		"innerColor": [195,53,43],
		"outerColor": [253,236,234],
        "row": 0,
        "column": 0
  },
  {
		"name": "Heal Instantly II",
		"prerequisites": ["Heal Instantly"],
		"uniques": ["[This Unit] heals [65] HP"],
		"unitTypes": ["Sword","Gunpowder","Mounted","Scout","Siege","Archery","Ranged Gunpowder","Armored","Melee Water","Ranged Water","Submarine"],
		"innerColor": [195,53,43],
		"outerColor": [253,236,234],
        "row": 1,
        "column": 0
  },
  {
		"name": "Heal Instantly III",
		"prerequisites": ["Heal Instantly II"],
		"uniques": ["[This Unit] heals [80] HP", "Doing so will consume this opportunity to choose a Promotion"],
		"unitTypes": ["Sword","Gunpowder","Mounted","Scout","Siege","Archery","Ranged Gunpowder","Armored","Melee Water","Ranged Water","Submarine"],
		"innerColor": [195,53,43],
		"outerColor": [253,236,234],
        "row": 2,
        "column": 0
  },

  //Ranged + Siege
  {
		"name": "Volley",
		"prerequisites": ["Accuracy I","Barrage I"],
		"uniques": ["[+50]% Strength <vs cities>"],
		"unitTypes": ["Siege"],
        "column": 3,
        "row": 1
  },
  {
		"name": "Volley II",
		"prerequisites": ["Volley"],
		"uniques": ["[+25]% Strength <vs cities>"],
		"unitTypes": ["Siege"],
        "column": 3,
        "row": 2
  },
  {
		"name": "Volley III",
		"prerequisites": ["Volley II"],
		"uniques": ["[+25]% Strength <vs cities>"],
		"unitTypes": ["Siege"],
        "column": 3,
        "row": 3
  },
  {
		"name": "Extended Range",
		"prerequisites": ["Accuracy III","Barrage III","Targeting II","Bombardment II", "Wolfpack II"],
		"uniques": ["[+1] Range"],
		"unitTypes": ["Archery","Ranged Gunpowder","Siege","Ranged Water","Submarine"],
        "column": 3,
        "row": 4
  },
  {
		"name": "Extended Range II",
		"prerequisites": ["Extended Range"],
		"uniques": ["[+1] Range <when fighting in [Friendly Land] tiles>"],
		"unitTypes": ["Archery","Ranged Gunpowder","Siege","Ranged Water","Submarine"],
        "column": 3,
        "row": 5
  },
  {
		"name": "Extended Range III",
		"prerequisites": ["Extended Range II"],
		"uniques": ["[+1] Range <when fighting in [Foreign Land] tiles>"],
		"unitTypes": ["Archery","Ranged Gunpowder","Siege","Ranged Water","Submarine"],
        "column": 3,
        "row": 6
  },
  {
		"name": "Indirect Fire",
		"prerequisites": ["Accuracy III", "Barrage III", "Bombardment II", "Targeting II"],
		"uniques": ["Ranged attacks may be performed over obstacles"],
		"unitTypes": ["Archery","Ranged Gunpowder","Siege","Ranged Water"],
        "column": 3,
        "row": 7
  },
  {
		"name": "Indirect Fire II",
		"prerequisites": ["Indirect Fire"],
		"uniques": ["Can see over obstacles"],
		"unitTypes": ["Archery","Ranged Gunpowder","Siege","Ranged Water"],
        "column": 3,
        "row": 8
  },
  {
		"name": "Indirect Fire III",
		"prerequisites": ["Indirect Fire II"],
		"uniques": ["[+50]% Strength <when attacking> <when fighting in [Fort] tiles>","[+50]% Strength <when attacking> <when fighting in [Citadel] tiles>"],
		"unitTypes": ["Archery","Ranged Gunpowder","Siege","Ranged Water"],
        "column": 3,
        "row": 9
  },
  //Melee/Mounted/Armor	
  {
		"name": "Amphibious",
		"prerequisites": ["Shock I", "Drill I"],
		"uniques": ["Eliminates combat penalty for attacking over a river", "Eliminates combat penalty for attacking across a coast"],
		"unitTypes": ["Sword","Gunpowder"],
        "column": 6,
        "row": 1
  },
  {
		"name": "Amphibious II",
		"prerequisites": ["Amphibious"],
		"uniques": ["[+1] Sight <when [Embarked]>", "May attack when embarked"],
		"unitTypes": ["Sword","Gunpowder"],
        "column": 6,
        "row": 2
  },
  {
		"name": "Amphibious III",
		"prerequisites": ["Amphibious II"],
		"uniques": ["[1] Movement point cost to disembark", "[1] Movement point cost to embark", "Double movement in [Coast] <for [Denmark] Civilizations>","Can enter ice tiles <for [Denmark] Civilizations>"],
		"unitTypes": ["Sword","Gunpowder"],
        "column": 6,
        "row": 3
  },
  {
		"name": "Charge",
		"prerequisites": ["Shock II","Drill II"],
		"uniques": ["[+33]% Strength <vs [Wounded] units>"],
		"unitTypes": ["Mounted","Armored"],
        "column": 6,
        "row": 4
  },
  {
		"name": "Charge II",
		"prerequisites": ["Charge"],
		"uniques": ["[+33]% to Flank Attack bonuses","[+17]% Strength <vs [Wounded] units>"],
		"unitTypes": ["Mounted","Armored"],
        "column": 6,
        "row": 5
  },
  {
		"name": "Charge III",
		"prerequisites": ["Charge II"],
		"uniques": ["Double movement in [{Featureless} {Grassland}]","Double movement in [{Featureless} {Plains}]"],
		"unitTypes": ["Mounted","Armored"],
        "column": 6,
        "row": 6
  },
  {
		"name": "Besiege",
		"prerequisites": ["Shock II","Drill II"],
		"uniques": ["[+50]% Strength <vs cities>"],
		"unitTypes": ["Sword","Gunpowder"],
        "column": 6,
        "row": 7
  },
  {
		"name": "Besiege II",
		"prerequisites": ["Besiege"],
		"uniques": ["[+25]% Strength <when defending> <when fighting in [Enemy Land] tiles>"],
		"unitTypes": ["Sword","Gunpowder"],
        "column": 6,
        "row": 8
  },
  {
		"name": "Besiege III",
		"prerequisites": ["Besiege II"],
		"uniques": ["[+50]% Strength <vs cities>"],
		"unitTypes": ["Sword","Gunpowder"],
        "column": 6,
        "row": 9
  },
  {
		"name": "Formation I",
		"prerequisites": ["Shock II","Drill II","Accuracy II","Barrage II"],
		"uniques": ["[+33]% Strength <vs [Mounted] units>", "[-50]% weight to this choice for AI decisions"],
		"unitTypes": ["Sword","Gunpowder","Mounted"],
        "column": 7,
        "row": 2
  },
  {
		"name": "Formation II",
		"prerequisites": ["Formation I"],
		"uniques": ["[+33]% Strength <vs [Mounted] units>"],
		"unitTypes": ["Sword","Gunpowder","Mounted"],
        "column": 7,
        "row": 3
  },
  {
		"name": "Formation III", //No clue what I could even add here to make Formation viable, honestly I don't want to bother with it
		"prerequisites": ["Formation II"],
		"uniques": ["[+33]% Strength <vs [Mounted] units>"],
		"unitTypes": ["Sword","Gunpowder","Mounted"],
        "column": 7,
        "row": 4
  },
  {
		"name": "Blitz",
		"prerequisites": ["Shock III","Drill III"],
		"uniques": ["[1] additional attacks per turn"],
		"unitTypes": ["Sword","Gunpowder","Mounted","Armored"],
        "column": 7,
        "row": 5
  },
  {
		"name": "Blitz II",
		"prerequisites": ["Blitz"],
		"uniques": ["[This Unit] gains [1] movement <upon damaging a [Military] unit>","[This Unit] heals [5] HP <upon damaging a [Military] unit>"],
		"unitTypes": ["Sword","Gunpowder","Mounted","Armored"],
        "column": 7,
        "row": 6
  },
  {
		"name": "Blitz III",
		"prerequisites": ["Blitz II"],
		"uniques": ["[1] additional attacks per turn"],
		"unitTypes": ["Sword","Gunpowder","Mounted","Armored"],
        "column": 7,
        "row": 7
  },
  {
		"name": "Woodsman",
		"prerequisites": ["Shock III","Drill III"],
		"uniques": ["Double movement in [Forest]","Double movement in [Jungle]"],
		"unitTypes": ["Sword","Gunpowder"],
        "column": 7,
        "row": 8
  },
  {
		"name": "Woodsman II",
		"prerequisites": ["Shock III","Drill III"],
		"uniques": ["Invisible to non-adjacent units <in [Vegetation] tiles>","Can see invisible [Woodsman II] units"],
		"unitTypes": ["Sword","Gunpowder"],
        "column": 7,
        "row": 8
  },
  {
		"name": "Woodsman III",
		"prerequisites": ["Shock III","Drill III"],
		"uniques": ["Can instantly construct a [Reforestation] improvement <requires [1] movement> <for [1] movement> <[3] times>"],
		"unitTypes": ["Sword","Gunpowder"],
        "column": 7,
        "row": 8
  },
]
